Metadata-Version: 1.0
Name: bartolina
Version: 0.0.1
Summary: Corrections for the redshift distortion
Home-page: https://github.com/exiliadadelsur/Bartolina
Author: ['Noelia Rocío Perez', 'Claudio Antonio Lopez Cortez']
Author-email: UNKNOWN
License: MIT
Keywords: space redshift,kaiser,finger of god,fog
Platform: UNKNOWN
